[
  {
    "id": "vitamina-d3",
    "name": "Vitamina D3",
    "brand": "NOW Foods",
    "dose": "2000 UI",
    "link": "https://gymbeam.ro/vitamina-d3-2000-iu-240-caps-now-foods.html",
    "notes": "dimineața, cu masă cu grăsimi · iarna / în funcție de analize"
  },
  {
    "id": "omega-3",
    "name": "Omega-3",
    "brand": "NOW Foods",
    "dose": "3000mg",
    "link": "https://gymbeam.ro/omega-3-now-foods.html",
    "notes": "1000mg dimineata cu micul dejun, 2000mg seara, creste HDL colesterolul bun"
  },
  {
    "id": "monacolina-k",
    "name": "Monacolina K Extract de orez rosu fermentat",
    "brand": "NOW Foods",
    "dose": "",
    "link": "https://www.emag.ro/red-yeast-rice-drojdie-de-orez-rosu-600-mg-now-foods-60-capsule-2761/pd/DFHLZ7MBM/",
    "notes": "1 capsula dimineata, 1 seara"
  },
  {
    "id": "magnesium-bisglycinate",
    "name": "Magneziu bisglicinat",
    "brand": "Doctor's Best",
    "dose": "200–350 mg Mg elementar",
    "link": "",
    "notes": "1–2h înainte de somn · scade doza dacă deranjează digestiv"
  },
  {
    "id": "l-theanine",
    "name": "L-teanină",
    "brand": "Jarrow",
    "dose": "100–200 mg",
    "link": "",
    "notes": "30–60 min înainte de somn · relaxare"
  },
  {
    "id": "ashwagandha",
    "name": "Ashwagandha (standardizată)",
    "brand": "KSM-66",
    "dose": "300–600 mg",
    "link": "",
    "notes": "seara, cu mâncare (sau 300 mg x2/zi) · evită în sarcină/alăptare; atenție la tiroidă"
  },
  {
    "id": "gaba",
    "name": "GABA",
    "brand": "NOW Foods",
    "dose": "100–300 mg",
    "link": "",
    "notes": "30–60 min înainte de somn · dovezi limitate; posibil GI/cefalee"
  }
]

